parasolr/__init__.py
parasolr/apps.py
parasolr/indexing.py
parasolr/pytest_plugin.py
parasolr/schema.py
parasolr/utils.py
parasolr/django/__init__.py
parasolr/django/disconnect_indexing.py
parasolr/django/indexing.py
parasolr/django/queryset.py
parasolr/django/signals.py
parasolr/django/solrclient.py
parasolr/django/util.py
parasolr/django/views.py
parasolr/django/tests/__init__.py
parasolr/django/tests/test_django.py
parasolr/django/tests/test_django_signals.py
parasolr/django/tests/test_models.py
parasolr/management/__init__.py
parasolr/management/commands/__init__.py
parasolr/management/commands/index.py
parasolr/management/commands/solr_schema.py
parasolr/query/__init__.py
parasolr/query/aliased_queryset.py
parasolr/query/queryset.py
parasolr/solr/__init__.py
parasolr/solr/admin.py
parasolr/solr/base.py
parasolr/solr/client.py
parasolr/solr/schema.py
parasolr/solr/update.py
parasolr/tests/__init__.py
parasolr/tests/test_commands.py
parasolr/tests/test_indexing.py
parasolr/tests/test_pytest_plugin.py
parasolr/tests/test_schema.py
parasolr/tests/test_utils.py
parasolr/tests/utils.py
parasolr-0.9.2.dist-info/LICENSE
parasolr-0.9.2.dist-info/METADATA
parasolr-0.9.2.dist-info/WHEEL
parasolr-0.9.2.dist-info/entry_points.txt
parasolr-0.9.2.dist-info/top_level.txt
parasolr-0.9.2.dist-info/RECORD
