Metadata-Version: 2.1
Name: parasolr
Version: 0.9.2
Summary: Lightweight python library for Solr indexing, searching and schema management with optional Django integration.
Home-page: https://github.com/Princeton-CDH/parasolr
Author: The Center for Digital Humanities at Princeton
Author-email: cdhdevteam@princeton.edu
License: Apache License, Version 2.0
Classifier: Environment :: Web Environment
Classifier: Development Status :: 4 - Beta
Classifier: Framework :: Django
Classifier: Framework :: Django :: 3.2
Classifier: Framework :: Django :: 4.0
Classifier: Framework :: Django :: 4.1
Classifier: Framework :: Django :: 4.2
Classifier: Framework :: Django :: 5.0
Classifier: Framework :: Pytest
Classifier: Intended Audience :: Developers
Classifier: License :: OSI Approved :: Apache Software License
Classifier: Operating System :: OS Independent
Classifier: Programming Language :: Python
Classifier: Programming Language :: Python :: 3
Classifier: Programming Language :: Python :: 3.9
Classifier: Programming Language :: Python :: 3.10
Classifier: Programming Language :: Python :: 3.11
Classifier: Topic :: Internet :: WWW/HTTP
Classifier: Topic :: Database
License-File: LICENSE
Requires-Dist: requests
Requires-Dist: addict
Requires-Dist: progressbar2
Provides-Extra: dev
Requires-Dist: pytest >=7 ; extra == 'dev'
Requires-Dist: pytest-cov ; extra == 'dev'
Requires-Dist: sphinx ; extra == 'dev'
Requires-Dist: sphinxcontrib-napoleon ; extra == 'dev'
Requires-Dist: sphinx-autodoc-typehints ; extra == 'dev'
Requires-Dist: pre-commit ; extra == 'dev'
Requires-Dist: django >=3.0 ; extra == 'dev'
Requires-Dist: pytest-django >=3.6 ; extra == 'dev'
Provides-Extra: django
Requires-Dist: django >=3.0 ; extra == 'django'
Requires-Dist: pytest-django >=3.6 ; extra == 'django'
Provides-Extra: test
Requires-Dist: pytest >=7 ; extra == 'test'
Requires-Dist: pytest-cov ; extra == 'test'
